{"Activities":[{"Index":1,"Duration":0,"Precedence":[],"Resources":[0,0,0,0]},{"Index":2,"Duration":4,"Precedence":[1],"Resources":[1,0,0,0]},{"Index":3,"Duration":3,"Precedence":[1],"Resources":[0,0,0,2]},{"Index":4,"Duration":10,"Precedence":[1],"Resources":[0,0,0,4]},{"Index":5,"Duration":10,"Precedence":[2],"Resources":[0,0,1,0]},{"Index":6,"Duration":5,"Precedence":[5],"Resources":[0,10,0,0]},{"Index":7,"Duration":1,"Precedence":[2],"Resources":[0,3,0,0]},{"Index":8,"Duration":7,"Precedence":[7],"Resources":[3,0,0,0]},{"Index":9,"Duration":4,"Precedence":[5],"Resources":[0,0,0,1]},{"Index":10,"Duration":5,"Precedence":[5],"Resources":[0,0,0,6]},{"Index":11,"Duration":7,"Precedence":[7],"Resources":[0,0,0,6]},{"Index":12,"Duration":10,"Precedence":[11],"Resources":[0,3,0,0]},{"Index":13,"Duration":2,"Precedence":[9],"Resources":[0,7,0,0]},{"Index":14,"Duration":4,"Precedence":[9],"Resources":[0,0,2,0]},{"Index":15,"Duration":5,"Precedence":[14],"Resources":[0,5,0,0]},{"Index":16,"Duration":5,"Precedence":[9],"Resources":[0,0,0,1]},{"Index":17,"Duration":4,"Precedence":[12],"Resources":[0,0,0,4]},{"Index":18,"Duration":3,"Precedence":[4],"Resources":[0,0,7,0]},{"Index":19,"Duration":7,"Precedence":[10,18],"Resources":[0,0,0,3]},{"Index":20,"Duration":6,"Precedence":[2],"Resources":[8,0,0,0]},{"Index":21,"Duration":2,"Precedence":[7,13],"Resources":[0,0,2,0]},{"Index":22,"Duration":5,"Precedence":[3],"Resources":[0,0,8,0]},{"Index":23,"Duration":8,"Precedence":[13,18,20],"Resources":[10,0,0,0]},{"Index":24,"Duration":3,"Precedence":[17,21],"Resources":[0,0,7,0]},{"Index":25,"Duration":3,"Precedence":[12],"Resources":[5,0,0,0]},{"Index":26,"Duration":2,"Precedence":[22,23],"Resources":[8,0,0,0]},{"Index":27,"Duration":10,"Precedence":[14,22,25],"Resources":[0,0,5,0]},{"Index":28,"Duration":3,"Precedence":[15,24,25],"Resources":[0,0,0,9]},{"Index":29,"Duration":5,"Precedence":[16,28],"Resources":[8,0,0,0]},{"Index":30,"Duration":5,"Precedence":[6,8,26],"Resources":[7,0,0,0]},{"Index":31,"Duration":1,"Precedence":[19,23,27],"Resources":[5,0,0,0]},{"Index":32,"Duration":0,"Precedence":[29,30,31],"Resources":[0,0,0,0]}],"Resources":[11,12,9,9]}